pydependence/__init__.py
pydependence/__main__.py
pydependence/_cli.py
pydependence/_colors.py
pydependence/_core/__init__.py
pydependence/_core/builtin.py
pydependence/_core/module_data.py
pydependence/_core/module_imports_ast.py
pydependence/_core/module_imports_loader.py
pydependence/_core/modules_resolver.py
pydependence/_core/modules_scope.py
pydependence/_core/requirements_map.py
pydependence/_core/requirements_out.py
pydependence/_core/utils.py
pydependence-0.5.0.dist-info/LICENSE
pydependence-0.5.0.dist-info/METADATA
pydependence-0.5.0.dist-info/WHEEL
pydependence-0.5.0.dist-info/top_level.txt
pydependence-0.5.0.dist-info/RECORD
