Metadata-Version: 2.1
Name: pydependence
Version: 0.5.0
Summary: Python local package dependency discovery, resolution and requirements generation.
Author-email: Nathan Michlo <nathanjmichlo@gmail.com>
License: MIT License
Project-URL: repository, https://github.com/nmichlo/pydependence
Classifier: Programming Language :: Python :: 3.8
Classifier: Programming Language :: Python :: 3.9
Classifier: Programming Language :: Python :: 3.10
Classifier: Programming Language :: Python :: 3.11
Classifier: Programming Language :: Python :: 3.12
Classifier: License :: OSI Approved :: MIT License
Classifier: Operating System :: OS Independent
Requires-Python: >=3.8
License-File: LICENSE
Requires-Dist: networkx
Requires-Dist: packaging
Requires-Dist: pydantic >=2.0.0
Requires-Dist: stdlib-list
Requires-Dist: typing-extensions
Provides-Extra: all
Requires-Dist: networkx ; extra == 'all'
Requires-Dist: packaging ; extra == 'all'
Requires-Dist: pydantic >=2.0.0 ; extra == 'all'
Requires-Dist: stdlib-list ; extra == 'all'
Requires-Dist: tomlkit ; extra == 'all'
Requires-Dist: typing-extensions ; extra == 'all'
Provides-Extra: core
Requires-Dist: networkx ; extra == 'core'
Requires-Dist: stdlib-list ; extra == 'core'
Requires-Dist: tomlkit ; extra == 'core'
Provides-Extra: dev
Requires-Dist: pre-commit ; extra == 'dev'
Provides-Extra: example-core-no-lazy
Requires-Dist: networkx ; extra == 'example-core-no-lazy'
Requires-Dist: packaging ; extra == 'example-core-no-lazy'
Requires-Dist: pydantic >=2.0.0 ; extra == 'example-core-no-lazy'
Requires-Dist: stdlib-list ; extra == 'example-core-no-lazy'
Requires-Dist: typing-extensions ; extra == 'example-core-no-lazy'
Provides-Extra: example-legacy
Requires-Dist: networkx ; extra == 'example-legacy'
Requires-Dist: packaging ; extra == 'example-legacy'
Requires-Dist: pydantic <2.0.0,>=1.0.0 ; extra == 'example-legacy'
Requires-Dist: stdlib-list ; extra == 'example-legacy'
Requires-Dist: tomlkit ; extra == 'example-legacy'
Requires-Dist: typing-extensions ; extra == 'example-legacy'
Provides-Extra: some
Requires-Dist: networkx ; extra == 'some'
Requires-Dist: packaging ; extra == 'some'
Requires-Dist: pydantic >=2.0.0 ; extra == 'some'
Requires-Dist: stdlib-list ; extra == 'some'
Requires-Dist: typing-extensions ; extra == 'some'
Provides-Extra: test
Requires-Dist: networkx ; extra == 'test'
Requires-Dist: packaging ; extra == 'test'
Requires-Dist: pydantic >=2.0.0 ; extra == 'test'
Requires-Dist: pytest-cov >=4 ; extra == 'test'
Requires-Dist: pytest >=6 ; extra == 'test'
Requires-Dist: stdlib-list ; extra == 'test'
Requires-Dist: tomlkit ; extra == 'test'
Requires-Dist: typing-extensions ; extra == 'test'
